emails_gdpr/__init__.py
emails_gdpr/exc.py
emails_gdpr/imap_utf7.py
emails_gdpr/logs.py
emails_gdpr/main.py
emails_gdpr/settings.py
emails_gdpr/utils.py
emails_gdpr-1.0.6.dist-info/AUTHORS.rst
emails_gdpr-1.0.6.dist-info/LICENSE
emails_gdpr-1.0.6.dist-info/METADATA
emails_gdpr-1.0.6.dist-info/WHEEL
emails_gdpr-1.0.6.dist-info/entry_points.txt
emails_gdpr-1.0.6.dist-info/top_level.txt
emails_gdpr-1.0.6.dist-info/RECORD
