Metadata-Version: 2.1
Name: emails-gdpr
Version: 1.0.6
Summary: UNKNOWN
Home-page: https://github.com/an0o0nym/emails-gdpr
Author: Damian P.
Author-email: an0o0nyme@gmail.com
License: MIT license
Keywords: emails gdpr general regulation data protection privacy right to be forgotten
Platform: UNKNOWN
Classifier: Programming Language :: Python :: 3
Classifier: Programming Language :: Python :: 3.5
Classifier: Development Status :: 4 - Beta
Classifier: License :: OSI Approved :: MIT License
Classifier: Operating System :: OS Independent
Classifier: Natural Language :: English
Requires-Dist: cachetools (==3.0.0)
Requires-Dist: email-normalize (==0.2.1)
Requires-Dist: tldextract (==2.2.0)
